pedon/__init__.py
pedon/_params.py
pedon/_typing.py
pedon/_version.py
pedon/py.typed
pedon/soil.py
pedon/soilmodel.py
pedon/datasets/soilsamples.csv
pedon-0.0.10.dist-info/licenses/LICENSE
pedon-0.0.10.dist-info/METADATA
pedon-0.0.10.dist-info/WHEEL
pedon-0.0.10.dist-info/top_level.txt
pedon-0.0.10.dist-info/RECORD
