Metadata-Version: 2.4
Name: pedon
Version: 0.0.10
Summary: Python package for (unsaturated) soil properties including pedotransfer functions
Author-email: Martin Vonk <vonk.mart@gmail.com>
License: MIT License
Project-URL: homepage, https://github.com/martinvonk/pedon
Project-URL: repository, https://github.com/martinvonk/pedon
Classifier: Programming Language :: Python :: 3 :: Only
Classifier: Programming Language :: Python :: 3.11
Classifier: Programming Language :: Python :: 3.12
Classifier: Programming Language :: Python :: 3.13
Classifier: Programming Language :: Python :: 3.14
Classifier: Topic :: Scientific/Engineering :: Hydrology
Classifier: Intended Audience :: Science/Research
Classifier: License :: OSI Approved :: MIT License
Classifier: Operating System :: OS Independent
Classifier: Typing :: Typed
Requires-Python: >=3.11
License-File: LICENSE
Requires-Dist: numpy
Requires-Dist: matplotlib
Requires-Dist: pandas
Requires-Dist: scipy
Provides-Extra: ruffing
Requires-Dist: ruff; extra == "ruffing"
Provides-Extra: typing
Requires-Dist: mypy; extra == "typing"
Requires-Dist: pandas-stubs; extra == "typing"
Provides-Extra: rosetta
Requires-Dist: httpx; extra == "rosetta"
Provides-Extra: pytesting
Requires-Dist: pytest>=7; extra == "pytesting"
Requires-Dist: pytest-cov; extra == "pytesting"
Requires-Dist: pytest-sugar; extra == "pytesting"
Requires-Dist: pedon[rosetta]; extra == "pytesting"
Provides-Extra: coveraging
Requires-Dist: coverage; extra == "coveraging"
Provides-Extra: documentation
Requires-Dist: sphinx>=8.2; extra == "documentation"
Requires-Dist: myst-parser; extra == "documentation"
Requires-Dist: nbsphinx; extra == "documentation"
Requires-Dist: ipykernel; extra == "documentation"
Requires-Dist: pandoc; extra == "documentation"
Provides-Extra: dev
Requires-Dist: pedon[pytesting,ruffing,typing]; extra == "dev"
Requires-Dist: tox; extra == "dev"
Dynamic: license-file
